ascson/__init__.py
ascson/ascsontypes/__init__.py
ascson/ascsontypes/_base.py
ascson/ascsontypes/bool.py
ascson/ascsontypes/dict.py
ascson/ascsontypes/float.py
ascson/ascsontypes/int.py
ascson/ascsontypes/list.py
ascson/ascsontypes/obj.py
ascson/ascsontypes/str.py
ascson/encoder.py
ascson/typecodes.py
ascson-0.0.1.dist-info/LICENSE
ascson-0.0.1.dist-info/METADATA
ascson-0.0.1.dist-info/WHEEL
ascson-0.0.1.dist-info/RECORD
