Metadata-Version: 2.3
Name: ascson
Version: 0.0.1
Summary: ASCii Serial Object Notation
License: MIT
Author: Rob Nelson
Author-email: nexisentertainment@gmail.com
Requires-Python: >=3.12,<4.0
Classifier: License :: OSI Approved :: MIT License
Classifier: Programming Language :: Python :: 3
Classifier: Programming Language :: Python :: 3.12
Classifier: Programming Language :: Python :: 3.13
